jiav_command/__init__.py
jiav_command/backend.py
jiav_backend_command-0.2.0.dist-info/METADATA
jiav_backend_command-0.2.0.dist-info/WHEEL
jiav_backend_command-0.2.0.dist-info/entry_points.txt
jiav_backend_command-0.2.0.dist-info/RECORD
